<DialogueTree xmlns:xsi="http://www.w3.org/2001/XMLSchema-instance" xsi:noNamespaceSchemaLocation="https://raw.githubusercontent.com/xen-42/outer-wilds-new-horizons/main/NewHorizons/Schemas/dialogue_schema.xsd">
	<NameField>SIGN</NameField>

	<DialogueNode>
		<Name>Start</Name>
		<EntryCondition>DEFAULT</EntryCondition>
		<Dialogue>
			<Page>I went for ... for ... <![CDATA[<i>mushrooms</i>]]>. Don't take my place! I'll be back soon. Get <![CDATA[<color=orange>new launch codes</color>]]> at the Observatory, Hornfels changed them at the last minute.</Page>
		</Dialogue>
	</DialogueNode>	
</DialogueTree>